{
  "file_info": {
    "file_path": "data/Libro Diario Trepat Diet.csv",
    "file_name": "Libro Diario Trepat Diet.csv",
    "erp_system": "Generic_ES",
    "total_columns": 71,
    "timestamp": "20250717_084329",
    "backup_created": "config\\backups\\dynamic_fields_config_backup_20250717_084331.yaml"
  },
  "original_mappings": {
    "Nº cuenta": {
      "field_type": "gl_account_number",
      "field_name": "Número cuenta contable",
      "confidence": 1.0
    },
    "Fecha registro": {
      "field_type": "entered_date",
      "field_name": "Fecha ingreso",
      "confidence": 0.8
    },
    "Tipo documento": {
      "field_type": "document_type",
      "field_name": "Tipo de documento",
      "confidence": 0.9
    },
    "Nº documento": {
      "field_type": "journal_id",
      "field_name": "ID de Asiento",
      "confidence": 1.0
    },
    "Descripción": {
      "field_type": "je_header_description",
      "field_name": "Descripción encabezado asiento",
      "confidence": 1.0
    },
    "Importe": {
      "field_type": "amount",
      "field_name": "Importe",
      "confidence": 0.9
    },
    "Id. usuario": {
      "field_type": "entered_by",
      "field_name": "Ingresado por",
      "confidence": 1.0
    },
    "Asiento post-cierre": {
      "field_type": "journal_id_line_number",
      "field_name": "Número de línea de Asiento",
      "confidence": 1.0
    },
    "Cantidad": {
      "field_type": "amount",
      "field_name": "Importe",
      "confidence": 0.7
    },
    "Importe IVA": {
      "field_type": "amount",
      "field_name": "Importe",
      "confidence": 1.0
    },
    "Cód. empresa": {
      "field_type": "company_code",
      "field_name": "Código compañía",
      "confidence": 1.0
    },
    "Nombre sección diario": {
      "field_type": "ledger",
      "field_name": "Libro contable",
      "confidence": 1.0
    },
    "Nº asiento": {
      "field_type": "je_header_description",
      "field_name": "Descripción encabezado asiento",
      "confidence": 1.0
    },
    "Importe debe": {
      "field_type": "amount_debit",
      "field_name": "Importe Debe",
      "confidence": 0.9
    },
    "Importe haber": {
      "field_type": "amount_credit",
      "field_name": "Importe Haber",
      "confidence": 0.9
    },
    "Fecha emisión documento": {
      "field_type": "journal_id",
      "field_name": "ID de Asiento",
      "confidence": 1.0
    },
    "Nº documento externo": {
      "field_type": "journal_id",
      "field_name": "ID de Asiento",
      "confidence": 1.0
    },
    "Cód. área impuesto": {
      "field_type": "amount_debit",
      "field_name": "Importe Debe",
      "confidence": 1.0
    },
    "Importe divisa-adicional": {
      "field_type": "amount",
      "field_name": "Importe",
      "confidence": 1.0
    },
    "Debe div.-adic.": {
      "field_type": "amount_debit",
      "field_name": "Importe Debe",
      "confidence": 1.0
    },
    "Haber div.-adic.": {
      "field_type": "amount_credit",
      "field_name": "Importe Haber",
      "confidence": 1.0
    },
    "Fecha/hora de última modificación": {
      "field_type": "effective_date",
      "field_name": "Fecha efectiva",
      "confidence": 1.0
    },
    "Nº asiento periodo": {
      "field_type": "period",
      "field_name": "Período",
      "confidence": 1.0
    },
    "Hasta Nº documento": {
      "field_type": "journal_id",
      "field_name": "ID de Asiento",
      "confidence": 1.0
    },
    "Desde Nº documento": {
      "field_type": "journal_id",
      "field_name": "ID de Asiento",
      "confidence": 1.0
    },
    "Descripción operación": {
      "field_type": "amount_credit",
      "field_name": "Importe Haber",
      "confidence": 1.0
    },
    "Genera criterio caja": {
      "field_type": "amount_credit",
      "field_name": "Importe Haber",
      "confidence": 1.0
    }
  },
  "confirmed_mappings": {
    "Nº cuenta": {
      "field_type": "gl_account_number",
      "confidence": 1.0,
      "source_erp": "Generic_ES",
      "field_name": "Número cuenta contable"
    },
    "Fecha registro": {
      "field_type": "entered_date",
      "confidence": 0.8,
      "source_erp": "Generic_ES",
      "field_name": "Fecha ingreso"
    },
    "Tipo documento": {
      "field_type": "document_type",
      "confidence": 0.9,
      "source_erp": "Generic_ES",
      "field_name": "Tipo de documento"
    },
    "Nº documento": {
      "field_type": "journal_id",
      "confidence": 1.0,
      "source_erp": "Generic_ES",
      "field_name": "ID de Asiento"
    },
    "Descripción": {
      "field_type": "je_header_description",
      "confidence": 1.0,
      "source_erp": "Generic_ES",
      "field_name": "Descripción encabezado asiento"
    },
    "Importe": {
      "field_type": "amount",
      "confidence": 0.9,
      "source_erp": "Generic_ES",
      "field_name": "Importe"
    },
    "Id. usuario": {
      "field_type": "entered_by",
      "confidence": 1.0,
      "source_erp": "Generic_ES",
      "field_name": "Ingresado por"
    },
    "Importe debe": {
      "field_type": "amount_debit",
      "confidence": 0.9,
      "source_erp": "Generic_ES",
      "field_name": "Importe Debe"
    },
    "Importe haber": {
      "field_type": "amount_credit",
      "confidence": 0.9,
      "source_erp": "Generic_ES",
      "field_name": "Importe Haber"
    }
  },
  "new_mappings": {
    "Nº mov.": {
      "field_type": "journal_id_line_number",
      "field_name": "Número de línea de Asiento",
      "confidence": 1.0,
      "source": "manual"
    }
  },
  "corrected_mappings": {
    "Nº asiento": {
      "original": {
        "field_type": "je_header_description",
        "confidence": 1.0,
        "source_erp": "Generic_ES",
        "field_name": "Descripción encabezado asiento"
      },
      "corrected": {
        "field_type": "journal_id",
        "field_name": "ID de Asiento",
        "confidence": 1.0,
        "source": "manual"
      }
    },
    "Fecha emisión documento": {
      "original": {
        "field_type": "journal_id",
        "confidence": 1.0,
        "source_erp": "Generic_ES",
        "field_name": "ID de Asiento"
      },
      "corrected": {
        "field_type": "effective_date",
        "field_name": "Fecha efectiva",
        "confidence": 1.0,
        "source": "manual"
      }
    }
  },
  "rejected_mappings": [
    {
      "column": "Cta. contrapartida",
      "reason": "user_rejected",
      "original_mapping": null
    },
    {
      "column": "Cód. dimensión global 1",
      "reason": "user_rejected",
      "original_mapping": null
    },
    {
      "column": "Cód. dimensión global 2",
      "reason": "user_rejected",
      "original_mapping": null
    },
    {
      "column": "Cód. origen",
      "reason": "user_rejected",
      "original_mapping": null
    },
    {
      "column": "Asiento automático",
      "reason": "user_rejected",
      "original_mapping": null
    },
    {
      "column": "Asiento post-cierre",
      "reason": "user_rejected",
      "original_mapping": {
        "field_type": "journal_id_line_number",
        "confidence": 1.0,
        "source_erp": "Generic_ES",
        "field_name": "Número de línea de Asiento"
      }
    },
    {
      "column": "Nº proyecto",
      "reason": "user_rejected",
      "original_mapping": null
    },
    {
      "column": "Cantidad",
      "reason": "user_rejected",
      "original_mapping": {
        "field_type": "amount",
        "confidence": 0.7,
        "source_erp": "Generic_ES",
        "field_name": "Importe"
      }
    },
    {
      "column": "Importe IVA",
      "reason": "user_rejected",
      "original_mapping": {
        "field_type": "amount",
        "confidence": 1.0,
        "source_erp": "Generic_ES",
        "field_name": "Importe"
      }
    },
    {
      "column": "Cód. empresa",
      "reason": "user_rejected",
      "original_mapping": {
        "field_type": "company_code",
        "confidence": 1.0,
        "source_erp": "Generic_ES",
        "field_name": "Código compañía"
      }
    },
    {
      "column": "Nombre sección diario",
      "reason": "user_rejected",
      "original_mapping": {
        "field_type": "ledger",
        "confidence": 1.0,
        "source_erp": "Generic_ES",
        "field_name": "Libro contable"
      }
    },
    {
      "column": "Cód. auditoría",
      "reason": "user_rejected",
      "original_mapping": null
    },
    {
      "column": "Tipo de registro gen.",
      "reason": "user_rejected",
      "original_mapping": null
    },
    {
      "column": "Grupo contable neg. gen.",
      "reason": "user_rejected",
      "original_mapping": null
    },
    {
      "column": "Grupo contable prod. gen.",
      "reason": "user_rejected",
      "original_mapping": null
    },
    {
      "column": "Tipo contrapartida",
      "reason": "user_rejected",
      "original_mapping": null
    },
    {
      "column": "Nº documento externo",
      "reason": "user_rejected",
      "original_mapping": {
        "field_type": "journal_id",
        "confidence": 1.0,
        "source_erp": "Generic_ES",
        "field_name": "ID de Asiento"
      }
    },
    {
      "column": "Tipo procedencia mov.",
      "reason": "user_rejected",
      "original_mapping": null
    },
    {
      "column": "Cód. procedencia mov.",
      "reason": "user_rejected",
      "original_mapping": null
    },
    {
      "column": "Nos. serie",
      "reason": "user_rejected",
      "original_mapping": null
    },
    {
      "column": "Cód. área impuesto",
      "reason": "user_rejected",
      "original_mapping": {
        "field_type": "amount_debit",
        "confidence": 1.0,
        "source_erp": "Generic_ES",
        "field_name": "Importe Debe"
      }
    },
    {
      "column": "Sujeto a impuesto",
      "reason": "user_rejected",
      "original_mapping": null
    },
    {
      "column": "Cód. grupo impuesto",
      "reason": "user_rejected",
      "original_mapping": null
    },
    {
      "column": "Impuesto de importación",
      "reason": "user_rejected",
      "original_mapping": null
    },
    {
      "column": "Grupo contable IVA negocio",
      "reason": "user_rejected",
      "original_mapping": null
    },
    {
      "column": "Grupo contable IVA prod.",
      "reason": "user_rejected",
      "original_mapping": null
    },
    {
      "column": "Importe divisa-adicional",
      "reason": "user_rejected",
      "original_mapping": {
        "field_type": "amount",
        "confidence": 1.0,
        "source_erp": "Generic_ES",
        "field_name": "Importe"
      }
    },
    {
      "column": "Debe div.-adic.",
      "reason": "user_rejected",
      "original_mapping": {
        "field_type": "amount_debit",
        "confidence": 1.0,
        "source_erp": "Generic_ES",
        "field_name": "Importe Debe"
      }
    },
    {
      "column": "Haber div.-adic.",
      "reason": "user_rejected",
      "original_mapping": {
        "field_type": "amount_credit",
        "confidence": 1.0,
        "source_erp": "Generic_ES",
        "field_name": "Importe Haber"
      }
    },
    {
      "column": "ID dim. asiento regularización",
      "reason": "user_rejected",
      "original_mapping": null
    },
    {
      "column": "Código socio IC",
      "reason": "user_rejected",
      "original_mapping": null
    },
    {
      "column": "Revertido",
      "reason": "user_rejected",
      "original_mapping": null
    },
    {
      "column": "Revertido por el movimiento n.º",
      "reason": "user_rejected",
      "original_mapping": null
    },
    {
      "column": "Nº movimiento revertido",
      "reason": "user_rejected",
      "original_mapping": null
    },
    {
      "column": "Id. grupo dimensiones",
      "reason": "user_rejected",
      "original_mapping": null
    },
    {
      "column": "Nº mov. corrección última dim.",
      "reason": "user_rejected",
      "original_mapping": null
    },
    {
      "column": "Nodo corrección últ. dim.",
      "reason": "user_rejected",
      "original_mapping": null
    },
    {
      "column": "Recuento de cambios de dimensiones",
      "reason": "user_rejected",
      "original_mapping": null
    },
    {
      "column": "Nº orden producción",
      "reason": "user_rejected",
      "original_mapping": null
    },
    {
      "column": "A/F Tipo mov.",
      "reason": "user_rejected",
      "original_mapping": null
    },
    {
      "column": "A/F Nº mov.",
      "reason": "user_rejected",
      "original_mapping": null
    },
    {
      "column": "Comentario",
      "reason": "user_rejected",
      "original_mapping": null
    },
    {
      "column": "Fecha/hora de última modificación",
      "reason": "user_rejected",
      "original_mapping": {
        "field_type": "effective_date",
        "confidence": 1.0,
        "source_erp": "Generic_ES",
        "field_name": "Fecha efectiva"
      }
    },
    {
      "column": "Nº asiento periodo",
      "reason": "user_rejected",
      "original_mapping": {
        "field_type": "period",
        "confidence": 1.0,
        "source_erp": "Generic_ES",
        "field_name": "Período"
      }
    },
    {
      "column": "Cód. país banco",
      "reason": "user_rejected",
      "original_mapping": null
    },
    {
      "column": "Nº efecto",
      "reason": "user_rejected",
      "original_mapping": null
    },
    {
      "column": "Hasta Nº documento",
      "reason": "user_rejected",
      "original_mapping": {
        "field_type": "journal_id",
        "confidence": 1.0,
        "source_erp": "Generic_ES",
        "field_name": "ID de Asiento"
      }
    },
    {
      "column": "Desde Nº documento",
      "reason": "user_rejected",
      "original_mapping": {
        "field_type": "journal_id",
        "confidence": 1.0,
        "source_erp": "Generic_ES",
        "field_name": "ID de Asiento"
      }
    },
    {
      "column": "Generado SII",
      "reason": "user_rejected",
      "original_mapping": null
    },
    {
      "column": "Régimen",
      "reason": "user_rejected",
      "original_mapping": null
    },
    {
      "column": "Tipo rectificativa",
      "reason": "user_rejected",
      "original_mapping": null
    },
    {
      "column": "Nº DUA",
      "reason": "user_rejected",
      "original_mapping": null
    },
    {
      "column": "Descripción operación",
      "reason": "user_rejected",
      "original_mapping": {
        "field_type": "amount_credit",
        "confidence": 1.0,
        "source_erp": "Generic_ES",
        "field_name": "Importe Haber"
      }
    },
    {
      "column": "Tipo factura",
      "reason": "user_rejected",
      "original_mapping": null
    },
    {
      "column": "Factura simplificada (Art. 7.2 y 7.3)",
      "reason": "user_rejected",
      "original_mapping": null
    },
    {
      "column": "Factura simplificada (Art. 6.1.d)",
      "reason": "user_rejected",
      "original_mapping": null
    },
    {
      "column": "Referencia externa",
      "reason": "user_rejected",
      "original_mapping": null
    },
    {
      "column": "Genera criterio caja",
      "reason": "user_rejected",
      "original_mapping": {
        "field_type": "amount_credit",
        "confidence": 1.0,
        "source_erp": "Generic_ES",
        "field_name": "Importe Haber"
      }
    },
    {
      "column": "Tipo bien inversión",
      "reason": "user_rejected",
      "original_mapping": null
    }
  ]
}